kismetanalyzer/__init__.py
kismetanalyzer/aplist.py
kismetanalyzer/clientlist.py
kismetanalyzer/devices.py
kismetanalyzer/model.py
kismetanalyzer/util.py
kismet_analyzer-0.4.1.dist-info/METADATA
kismet_analyzer-0.4.1.dist-info/WHEEL
kismet_analyzer-0.4.1.dist-info/entry_points.txt
kismet_analyzer-0.4.1.dist-info/top_level.txt
kismet_analyzer-0.4.1.dist-info/RECORD
