Metadata-Version: 2.1
Name: kismet-analyzer
Version: 0.4.1
Summary: Library for parsing kismet results from the .kismet database file.
Home-page: https://bitbucket.org/cbless/kismetanalyzer
Author: Christoph Bless
Author-email: bitbucket@cbless.de
License: GPLv3
Platform: UNKNOWN
Requires-Dist: fastkml
Requires-Dist: pygeoif
Requires-Dist: lxml
